arun/Logging.py
arun/Manage.py
arun/Runner.py
arun/Service.py
arun/__init__.py
arun-0.1.0.dist-info/licenses/AUTHORS.rst
arun-0.1.0.dist-info/licenses/LICENSE
arun-0.1.0.dist-info/METADATA
arun-0.1.0.dist-info/WHEEL
arun-0.1.0.dist-info/top_level.txt
arun-0.1.0.dist-info/RECORD
