Metadata-Version: 2.4
Name: arun
Version: 0.1.0
Summary: Make asyncio service
Home-page: https://github.com/zloidemon/arun/
Author: Veniamin Gvozdikov
Author-email: g.veniamin@googlemail.com
License: BSD
Keywords: arun
Platform: any
Classifier: Intended Audience :: System Administrators
Classifier: License :: OSI Approved :: BSD License
Classifier: Programming Language :: Python :: 3
Classifier: Programming Language :: Python :: 3.11
Classifier: Programming Language :: Python :: 3.12
Classifier: Programming Language :: Python :: 3.13
Classifier: Programming Language :: Python
Classifier: Topic :: System :: Boot
Classifier: Topic :: System :: Systems Administration
License-File: LICENSE
License-File: AUTHORS.rst
Requires-Dist: aiohttp_jrpc>=0.2.0
Requires-Dist: setproctitle>=1.3.6
Dynamic: author
Dynamic: author-email
Dynamic: classifier
Dynamic: description
Dynamic: home-page
Dynamic: keywords
Dynamic: license
Dynamic: license-file
Dynamic: platform
Dynamic: requires-dist
Dynamic: summary
